Metadata-Version: 1.0
Name: stackdistiller
Version: 0.12
Summary: A data extraction and transformation library for OpenStack notifications
Home-page: https://github.com/stackforge/stacktach-stackdistiller
Author: Monsyne Dragon
Author-email: mdragon@rackspace.com
License: Apache-2
Keywords: OpenStack
Platform: UNKNOWN
